pfxbrick/__init__.py
pfxbrick/pfx.py
pfxbrick/pfxaction.py
pfxbrick/pfxbrick.py
pfxbrick/pfxconfig.py
pfxbrick/pfxdict.py
pfxbrick/pfxfiles.py
pfxbrick/pfxhelpers.py
pfxbrick/pfxmsg.py
pfxbrick-0.6.2.dist-info/DESCRIPTION.rst
pfxbrick-0.6.2.dist-info/METADATA
pfxbrick-0.6.2.dist-info/RECORD
pfxbrick-0.6.2.dist-info/WHEEL
pfxbrick-0.6.2.dist-info/metadata.json
pfxbrick-0.6.2.dist-info/top_level.txt
