Metadata-Version: 2.0
Name: pfxbrick
Version: 0.6.2
Summary: A python API for host control of USB connected PFx Bricks.
Home-page: https://github.com/fx-bricks/pfx-brick-py
Author: Fx Bricks Inc.
Author-email: info@fxbricks.com
License: MIT
Platform: UNKNOWN
Classifier: Development Status :: 3 - Alpha
Classifier: Natural Language :: English
Classifier: Operating System :: OS Independent
Classifier: Programming Language :: Python :: 3.6
Classifier: Intended Audience :: Developers
Classifier: License :: OSI Approved :: MIT License
Requires-Dist: hidapi
